{
    "name": "QuestionCategory",
    "fields": [
        {
            "fieldName": "label",
            "fieldType": "String"
        },
        {
            "fieldName": "level",
            "fieldType": "Integer"
        }
    ],
    "relationships": [
        {
            "relationshipType": "one-to-many",
            "relationshipName": "soons",
            "otherEntityName": "questionCategory",
            "otherEntityRelationshipName": "father"
        },
        {
            "relationshipType": "many-to-one",
            "relationshipName": "father",
            "otherEntityName": "questionCategory",
            "otherEntityField": "id"
        },
        {
            "relationshipType": "many-to-one",
            "relationshipName": "father",
            "otherEntityName": "questionCategory",
            "otherEntityField": "id"
        },
        {
            "relationshipType": "one-to-many",
            "relationshipName": "soons",
            "otherEntityName": "questionCategory",
            "otherEntityRelationshipName": "father"
        },
        {
            "relationshipType": "one-to-many",
            "relationshipName": "questions",
            "otherEntityName": "question",
            "otherEntityRelationshipName": "category"
        }
    ],
    "changelogDate": "20180903080300",
    "entityTableName": "question_category",
    "dto": "mapstruct",
    "pagination": "no",
    "service": "serviceImpl",
    "jpaMetamodelFiltering": false,
    "fluentMethods": true,
    "clientRootFolder": "",
    "applications": "*",
    "angularJSSuffix": "pulse"
}